awesome_autodl/__init__.py
awesome_autodl/bins/__init__.py
awesome_autodl/bins/list_email.py
awesome_autodl/bins/list_email_FIE_202203.py
awesome_autodl/bins/show_infos.py
awesome_autodl/bins/statistics.py
awesome_autodl/data_cls/__init__.py
awesome_autodl/data_cls/abbrv.py
awesome_autodl/data_cls/paper.py
awesome_autodl/raw_data/__init__.py
awesome_autodl/utils/__init__.py
awesome_autodl/utils/check.py
awesome_autodl/utils/filter.py
awesome_autodl/utils/fix_invalid_email.py
awesome_autodl/utils/yaml.py
awesome_autodl-1.2.data/data/awesome_autodl/raw_data/abbrv.bib
awesome_autodl-1.2.data/data/awesome_autodl/raw_data/abbrv.yaml
awesome_autodl-1.2.data/data/awesome_autodl/raw_data/papers/Automated_Data_Engineering.yaml
awesome_autodl-1.2.data/data/awesome_autodl/raw_data/papers/Automated_Deployment.yaml
awesome_autodl-1.2.data/data/awesome_autodl/raw_data/papers/Automated_Maintenance.yaml
awesome_autodl-1.2.data/data/awesome_autodl/raw_data/papers/Automated_Problem_Formulation.yaml
awesome_autodl-1.2.data/data/awesome_autodl/raw_data/papers/Hyperparameter_Optimization.yaml
awesome_autodl-1.2.data/data/awesome_autodl/raw_data/papers/Neural_Architecture_Search.yaml
awesome_autodl-1.2.dist-info/LICENSE
awesome_autodl-1.2.dist-info/METADATA
awesome_autodl-1.2.dist-info/WHEEL
awesome_autodl-1.2.dist-info/top_level.txt
awesome_autodl-1.2.dist-info/RECORD
