Metadata-Version: 2.1
Name: awesome-autodl
Version: 1.2
Summary: Package for Automated Deep Learning Paper Analysis
Home-page: https://github.com/D-X-Y/Awesome-AutoDL
Author: Xuanyi Dong
Author-email: dongxuanyi888@gmail.com
License: MIT Licence
Keywords: NAS Dataset API DeepLearning
Platform: UNKNOWN
Classifier: Programming Language :: Python
Classifier: Programming Language :: Python :: 3
Classifier: Topic :: Database
Classifier: Topic :: Scientific/Engineering :: Artificial Intelligence
Classifier: License :: OSI Approved :: MIT License
Requires-Python: >=3.6
Requires-Dist: pyyaml (>=5.0.0)
